{
    "gui": {
        "editor_gaphas": {
            "name": {
                "rel_pos": {
                    "__jsonqualname__": "__builtin__.tuple", 
                    "items": [
                        1.117778151236223, 
                        1.1177781512362266
                    ]
                }, 
                "size": {
                    "__jsonqualname__": "__builtin__.tuple", 
                    "items": [
                        22.355563024724535, 
                        11.177781512362268
                    ]
                }
            }, 
            "rel_pos": {
                "__jsonqualname__": "__builtin__.tuple", 
                "items": [
                    115.22640066102485, 
                    31.225008313403574
                ]
            }, 
            "size": {
                "__jsonqualname__": "__builtin__.tuple", 
                "items": [
                    27.94445378090567, 
                    27.94445378090567
                ]
            }
        }, 
        "show_content": {}
    }, 
    "income": {
        "gui": {
            "editor_gaphas": {
                "rel_pos": {
                    "__jsonqualname__": "__builtin__.tuple", 
                    "items": [
                        0.5588890756181134, 
                        2.794445378090567
                    ]
                }
            }
        }
    }, 
    "input_data_port0": {
        "gui": {
            "editor_gaphas": {
                "rel_pos": {
                    "__jsonqualname__": "__builtin__.tuple", 
                    "items": [
                        0.5588890756181134, 
                        25.150008402815104
                    ]
                }
            }
        }
    }, 
    "outcome-1": {
        "gui": {
            "editor_gaphas": {
                "rel_pos": {
                    "__jsonqualname__": "__builtin__.tuple", 
                    "items": [
                        27.385564705287557, 
                        18.554341741504206
                    ]
                }
            }
        }
    }, 
    "outcome-2": {
        "gui": {
            "editor_gaphas": {
                "rel_pos": {
                    "__jsonqualname__": "__builtin__.tuple", 
                    "items": [
                        27.385564705287557, 
                        9.263964629038076
                    ]
                }
            }
        }
    }, 
    "outcome0": {
        "gui": {
            "editor_gaphas": {
                "rel_pos": {
                    "__jsonqualname__": "__builtin__.tuple", 
                    "items": [
                        22.245450454022123, 
                        0.5588890756181134
                    ]
                }
            }
        }
    }, 
    "outcome1": {
        "gui": {
            "editor_gaphas": {
                "rel_pos": {
                    "__jsonqualname__": "__builtin__.tuple", 
                    "items": [
                        21.91462757040779, 
                        27.385564705287557
                    ]
                }
            }
        }
    }
}