{
    "gui": {
        "editor_gaphas": {
            "name": {
                "rel_pos": {
                    "__jsonqualname__": "__builtin__.tuple", 
                    "items": [
                        1.2647545881177085, 
                        1.2647545881177085
                    ]
                }, 
                "size": {
                    "__jsonqualname__": "__builtin__.tuple", 
                    "items": [
                        16.99369210870304, 
                        8.49684605435152
                    ]
                }
            }, 
            "rel_pos": {
                "__jsonqualname__": "__builtin__.tuple", 
                "items": [
                    19.402538549668446, 
                    75.72432555278617
                ]
            }, 
            "size": {
                "__jsonqualname__": "__builtin__.tuple", 
                "items": [
                    31.618864702942712, 
                    31.672383828899306
                ]
            }
        }
    }, 
    "income": {
        "gui": {
            "editor_gaphas": {
                "rel_pos": {
                    "__jsonqualname__": "__builtin__.tuple", 
                    "items": [
                        0.5867530419605643, 
                        7.183651603607601
                    ]
                }
            }
        }
    }, 
    "input_data_port1": {
        "gui": {
            "editor_gaphas": {
                "rel_pos": {
                    "__jsonqualname__": "__builtin__.tuple", 
                    "items": [
                        0.5867530419605643, 
                        17.418534411420616
                    ]
                }
            }
        }
    }, 
    "input_data_port3": {
        "gui": {
            "editor_gaphas": {
                "rel_pos": {
                    "__jsonqualname__": "__builtin__.tuple", 
                    "items": [
                        0, 
                        25.980988182369618
                    ]
                }
            }
        }
    }, 
    "outcome-1": {
        "gui": {
            "editor_gaphas": {
                "rel_pos": {
                    "__jsonqualname__": "__builtin__.tuple", 
                    "items": [
                        19.11790362229092, 
                        0.5867530419605643
                    ]
                }
            }
        }
    }, 
    "outcome-2": {
        "gui": {
            "editor_gaphas": {
                "rel_pos": {
                    "__jsonqualname__": "__builtin__.tuple", 
                    "items": [
                        17.418534411420616, 
                        0.5867530419605643
                    ]
                }
            }
        }
    }, 
    "outcome0": {
        "gui": {
            "editor_gaphas": {
                "rel_pos": {
                    "__jsonqualname__": "__builtin__.tuple", 
                    "items": [
                        30.986487408883857, 
                        3.5971213491352625
                    ]
                }
            }
        }
    }, 
    "output_data_port0": {
        "gui": {
            "editor_gaphas": {
                "rel_pos": {
                    "__jsonqualname__": "__builtin__.tuple", 
                    "items": [
                        30.986487408883857, 
                        7.533528180420996
                    ]
                }
            }
        }
    }, 
    "output_data_port2": {
        "gui": {
            "editor_gaphas": {
                "rel_pos": {
                    "__jsonqualname__": "__builtin__.tuple", 
                    "items": [
                        30.986487408883857, 
                        14.383891330479031
                    ]
                }
            }
        }
    }
}